{
  "@context": "https://schema.org",
  "@type": "FAQPage",
  "name": "I didn't go to the doctor right after my delivery accident—is it too late?",
  "description": "It's not too late, but every day you wait strengthens the insurance company's defense. Seek medical attention immediately and specify the work-related cause of ",
  "url": "https://justworkcomplaw.com//faq/general-i-didn-t-go-to-the-doctor-right-after-my-delivery-accident-is-it-too-late-97",
  "mainEntity": [
    {
      "@type": "Question",
      "name": "I didn't go to the doctor right after my delivery accident—is it too late?",
      "acceptedAnswer": {
        "@type": "Answer",
        "text": "It's not too late, but every day you wait strengthens the insurance company's defense. Seek medical attention immediately and specify the work-related cause of your injury to create a formal paper trail."
      }
    }
  ]
}